abstractMLBaseModelTask/__init__.py
abstractMLBaseModelTask/abstractMLBaseModel.py
abstractMLBaseModelTask/comprehensibility_analysis.py
abstractMLBaseModelTask/functionality_analysis.py
abstractMLBaseModelTask/neuralNetworkModel.py
abstractMLBaseModelTask-0.2.dist-info/METADATA
abstractMLBaseModelTask-0.2.dist-info/WHEEL
abstractMLBaseModelTask-0.2.dist-info/top_level.txt
abstractMLBaseModelTask-0.2.dist-info/RECORD
